[{"long":-7.934656,"lat":37.017493,"duration":8},{"long":-7.934405,"lat":37.01759,"duration":8},{"long":-7.934405,"lat":37.01759,"duration":25},{"long":-7.934736,"lat":37.018139,"duration":25},{"long":-7.934959,"lat":37.018473,"duration":25},{"long":-7.934959,"lat":37.018473,"duration":14},{"long":-7.93494,"lat":37.0186,"duration":14},{"long":-7.934854,"lat":37.018774,"duration":14},{"long":-7.934457,"lat":37.019041,"duration":14},{"long":-7.934457,"lat":37.019041,"duration":8},{"long":-7.934436,"lat":37.019175,"duration":8},{"long":-7.934427,"lat":37.019229,"duration":8},{"long":-7.934392,"lat":37.019375,"duration":8},{"long":-7.934364,"lat":37.019583,"duration":8},{"long":-7.934364,"lat":37.019583,"duration":0},{"long":-7.934364,"lat":37.019583,"duration":0}]